<layer>
  <name>laboreiro_mdt_svf</name>
  <id>LayerInfoImpl-3c310cc7:1841b34ee87:-7f48</id>
  <type>RASTER</type>
  <defaultStyle>
    <id>StyleInfoImpl-3c310cc7:1841b34ee87:-7f49</id>
  </defaultStyle>
  <resource class="coverage">
    <id>CoverageInfoImpl-3c310cc7:1841b34ee87:-7f4a</id>
  </resource>
  <queryable>true</queryable>
  <opaque>false</opaque>
  <attribution>
    <logoWidth>0</logoWidth>
    <logoHeight>0</logoHeight>
  </attribution>
  <dateCreated>2022-10-27 21:10:06.852 UTC</dateCreated>
</layer>